{
  "get-carreers": [
    {
      "name": "CBC",
      "id": 0
    },
    {
      "name": "DG",
      "id": 1
    },
    {
      "name": "DInd",
      "id": 2
    },
    {
      "name": "DP",
      "id": 3
    },
    {
      "name": "Arq",
      "id": 4
    },
    {
      "name": "DI",
      "id": 5
    },
    {
      "name": "DIyS",
      "id": 6
    },
    {
      "name": "DT",
      "id": 7
    }
  ],
  "get-subjects": [
    {
      "carreer": 0,
      "subjects": [
        {
          "name": "Análisis Matemático II",
          "id": 0
        },
        {
          "name": "Álgebra II",
          "id": 1
        },
        {
          "name": "Física I",
          "id": 2
        }
      ]
    },
    {
      "carreer": 1,
      "subjects": [
        {
          "name": "Probabilidad y Estadística",
          "id": 3
        },
        {
          "name": "Electromagnetismo",
          "id": 4
        },
        {
          "name": "Análisis de Circuitos",
          "id": 5
        }
      ]
    }
  ],
  "get-courses": [
    {
      "subject": 0,
      "courses": [
        {
          "name": "Charmander",
          "id": 0
        },
        {
          "name": "Squirtle",
          "id": 1
        },
        {
          "name": "Bulbasaur",
          "id": 2
        }
      ]
    },
    {
      "subject": 1,
      "courses": [
        {
          "name": "Treecko",
          "id": 3
        },
        {
          "name": "Torchic",
          "id": 4
        },
        {
          "name": "Mudkip",
          "id": 5
        }
      ]
    }
  ],
  "get-course-info": [
    {
      "course": 0,
      "email": "no_tiene_resenias@gmail.com",
      "shift": 3,
      "mean": 2.3,
      "reviews": [
        {
          "year": "2021",
          "content": "Me recomendaron un drive para bajar programas piratas que está re piola. 10/10.",
          "rate": "2",
          "id": 1
        },
        {
          "year": "2019",
          "content": "Me dormí unas siestas tremendas en las teóricas pero igual aprobé, no me quejo.",
          "rate": "1",
          "id": 2
        }
      ]
    },
    {
      "course": 0,
      "email": "tiene_resenias@gmail.com",
      "shift": 3,
      "mean": 2.3,
      "own_review": {
        "year": "2020",
        "content": "Me reprobó por un diseño de una aspiradora, malísimo.",
        "rate": "0",
        "id": 0
      },
      "reviews": [
        {
          "year": "2021",
          "content": "Me recomendaron un drive para bajar programas piratas que está re piola. 10/10.",
          "rate": "2",
          "id": 1
        },
        {
          "year": "2019",
          "content": "Me dormí unas siestas tremendas en las teóricas pero igual aprobé, no me quejo.",
          "rate": "1",
          "id": 2
        }
      ]
    }
  ],
  "delete-review": {},
  "create-review": {
    "year": "2020",
    "content": "Re fácil esta cátedra.",
    "rate": 2,
    "email": "example@gmail.com"
  }
}